contextlib_chdir.py
contextlib_chdir-1.0.1.dist-info/WHEEL
contextlib_chdir-1.0.1.dist-info/METADATA
contextlib_chdir-1.0.1.dist-info/RECORD
