Metadata-Version: 2.1
Name: contextlib-chdir
Version: 1.0.1
Summary: Backport of contextlib.chdir stdlib class added in Python3.11.
License: BSD-3-License
Author: Álvaro Mondéjar Rubio
Author-email: mondejar1994@gmail.com
Requires-Python: >=3.6,<4.0
Classifier: License :: Other/Proprietary License
Classifier: Programming Language :: Python :: 3
Classifier: Programming Language :: Python :: 3.6
Classifier: Programming Language :: Python :: 3.7
Classifier: Programming Language :: Python :: 3.8
Classifier: Programming Language :: Python :: 3.9
Classifier: Programming Language :: Python :: 3.10
